fitbit/__init__.py
fitbit/api/__init__.py
fitbit/api/activity_api.py
fitbit/api/activity_intraday_time_series_api.py
fitbit/api/activity_time_series_api.py
fitbit/api/auth_api.py
fitbit/api/body_and_weight_api.py
fitbit/api/body_and_weight_time_series_api.py
fitbit/api/devices_api.py
fitbit/api/food_and_water_api.py
fitbit/api/food_and_water_time_series_api.py
fitbit/api/friends_api.py
fitbit/api/heart_rate_intraday_time_series_api.py
fitbit/api/heart_rate_time_series_api.py
fitbit/api/sleep_api.py
fitbit/api/subscriptions_api.py
fitbit/api/user_api.py
fitbit/api_client.py
fitbit/configuration.py
fitbit/models/__init__.py
fitbit/models/oauth2_introspect_body.py
fitbit/models/profile_json_body.py
fitbit/rest.py
py_fitbit-1.0.1.dist-info/entry_points.txt
py_fitbit-1.0.1.dist-info/WHEEL
py_fitbit-1.0.1.dist-info/METADATA
py_fitbit-1.0.1.dist-info/RECORD
