Metadata-Version: 2.1
Name: py-fitbit
Version: 1.0.1
Summary: Python bindings for Fitbit Web API
Home-page: https://github.com/j-rossi-nl/py-fitbit
License: Apache-2.0
Author: Team
Author-email: j.rossi@uva.nl
Requires-Python: >=3.8,<4.0
Classifier: Development Status :: 3 - Alpha
Classifier: License :: OSI Approved :: Apache Software License
Classifier: Programming Language :: Python :: 3
Classifier: Programming Language :: Python :: 3.10
Classifier: Programming Language :: Python :: 3.8
Classifier: Programming Language :: Python :: 3.9
Requires-Dist: certifi (>=14.05.14)
Requires-Dist: click (>=8.0.1)
Requires-Dist: python-dateutil (>=2.5.3)
Requires-Dist: python-dotenv (>=0.19.2,<0.20.0)
Requires-Dist: setuptools (>=21.0.0)
Requires-Dist: six (>=1.10)
Requires-Dist: urllib3 (>=1.15.1)
Project-URL: Changelog, https://github.com/j-rossi-nl/py-fitbit/releases
Project-URL: Documentation, https://github.com/j-rossi-nl/py-fitbit
Project-URL: Repository, https://github.com/j-rossi-nl/py-fitbit
